runner.py-0.5.dist-info/LICENSE.txt
runner.py-0.5.dist-info/METADATA
runner.py-0.5.dist-info/RECORD
runner.py-0.5.dist-info/WHEEL
runner.py-0.5.dist-info/top_level.txt
runnerpy/__init__.py
runnerpy/__main__.py
runnerpy/colors.py
runnerpy/procs.py
runnerpy/runner.py
