Metadata-Version: 2.1
Name: runner.py
Version: 0.5
Summary: runner.py Run, Attach, Schedule, Repeat, Chain and React to commands.
Home-page: https://github.com/mariocesar/runner.py
Author: Mario César Señoranis Ayala
Author-email: mariocesar.c50@gmail.com
License: MIT
Keywords: runner process asyncio
Platform: UNKNOWN
Classifier: Development Status :: 3 - Alpha
Classifier: Intended Audience :: Developers
Classifier: Programming Language :: Python
Classifier: Programming Language :: Python :: 3
Classifier: Programming Language :: Python :: 3.6
Classifier: License :: OSI Approved :: MIT License
Classifier: Topic :: Software Development :: Libraries :: Python Modules
Requires-Python: >=3.6
